defn/VERSION
defn/__init__.py
defn/cli.py
defn/init.py
defn/aws/__init__.py
defn/aws/organizations.py
defn/aws/sso.py
defn/aws/stack.py
defn-0.0.1a7.dist-info/METADATA
defn-0.0.1a7.dist-info/WHEEL
defn-0.0.1a7.dist-info/entry_points.txt
defn-0.0.1a7.dist-info/namespace_packages.txt
defn-0.0.1a7.dist-info/top_level.txt
defn-0.0.1a7.dist-info/RECORD
